sankhyaakaara/__init__.py
sankhyaakaara/components.py
sankhyaakaara/converter.py
sankhyaakaara/languages.py
sankhyaakaara/numerals.py
sankhyaakaara/sandhi.py
sankhyaakaara/data/large.csv
sankhyaakaara/data/sandhi.csv
sankhyaakaara/data/two_digit.csv
sankhyaakaara-0.1.1.dist-info/LICENSE
sankhyaakaara-0.1.1.dist-info/METADATA
sankhyaakaara-0.1.1.dist-info/WHEEL
sankhyaakaara-0.1.1.dist-info/top_level.txt
sankhyaakaara-0.1.1.dist-info/RECORD
